LICENSE
README.md
setup.cfg
setup.py
pescea/__init__.py
pescea/controller.py
pescea/datagram.py
pescea/discovery.py
pescea/message.py
pescea/udp_endpoints.py
pescea.egg-info/PKG-INFO
pescea.egg-info/SOURCES.txt
pescea.egg-info/dependency_links.txt
pescea.egg-info/requires.txt
pescea.egg-info/top_level.txt