Metadata-Version: 2.1
Name: pescea
Version: 1.0.12
Summary: A python interface to the Escea fireplace controllers
Home-page: https://github.com/lazdavila/pescea
Download-URL: https://github.com/lazdavila/pescea/archive/refs/tags/v1.0.12.tar.gz
Author: Laz Davila
Author-email: laz.davila@gmail.com
License: gpl-3.0
Keywords: Escea,IoT
Classifier: Development Status :: 5 - Production/Stable
Classifier: Intended Audience :: Developers
Classifier: Topic :: Home Automation
Classifier: Topic :: System :: Hardware
Classifier: Operating System :: OS Independent
Classifier: License :: OSI Approved :: GNU General Public License v3 or later (GPLv3+)
Classifier: Programming Language :: Python :: 3.9
Classifier: Programming Language :: Python :: 3.10
Requires-Python: >=3.9
License-File: LICENSE
